kak_lsp_diags.py
kak_lsp_diags-1.1.2.dist-info/METADATA
kak_lsp_diags-1.1.2.dist-info/WHEEL
kak_lsp_diags-1.1.2.dist-info/entry_points.txt
kak_lsp_diags-1.1.2.dist-info/licenses/LICENSE
kak_lsp_diags-1.1.2.dist-info/RECORD
