Metadata-Version: 2.4
Name: kak-lsp-diags
Version: 1.1.2
Summary: Kakoune plugin for LSP hover diagnostics
Project-URL: Repository, https://codeberg.org/ficd/kak-lsp-diags
Author-email: Daniel Fichtinger <daniel@ficd.sh>
License-Expression: ISC
License-File: LICENSE
Keywords: kakoune,lsp,plugin
Requires-Python: >=3.11
